logmonitor/__init__.py
logmonitor/admin.py
logmonitor/apps.py
logmonitor/middleware.py
logmonitor/models.py
logmonitor/signals.py
logmonitor/tests.py
logmonitor/urls.py
logmonitor/utils.py
logmonitor/locale/en/LC_MESSAGES/django.mo
logmonitor/locale/en/LC_MESSAGES/django.po
logmonitor/locale/es/LC_MESSAGES/django.mo
logmonitor/locale/es/LC_MESSAGES/django.po
logmonitor/migrations/0001_initial.py
logmonitor/migrations/__init__.py
logmonitor/static/logmonitor/js/copiar_json.js
logmonitor/templates/admin/logmonitor/change_form.html
logmonitor/templates/admin/logmonitor/change_form_object_tools.html
logmonitor/templates/admin/logmonitor/submit_line.html
logmonitor/templates/django_admin_listfilter_dropdown/dropdown_filter.html
django_logmonitor-1.2.2.dist-info/LICENSE
django_logmonitor-1.2.2.dist-info/METADATA
django_logmonitor-1.2.2.dist-info/WHEEL
django_logmonitor-1.2.2.dist-info/top_level.txt
django_logmonitor-1.2.2.dist-info/RECORD
