Metadata-Version: 2.1
Name: django-logmonitor
Version: 1.2.2
Summary: Utilidad Django para monitorear y auditar las acciones de los usuarios en tus modelos.
Home-page: https://github.com/JaviPulido/LogMonitor
Author: Javier L. Pulido
Author-email: grupol2st@gmail.com
License: MIT
Keywords: logs auditoria audit monitoreo utilidad herramientas Python Django
Classifier: Development Status :: 5 - Production/Stable
Classifier: Environment :: Web Environment
Classifier: Framework :: Django
Classifier: Framework :: Django :: 3.2
Classifier: Framework :: Django :: 4.0
Classifier: Framework :: Django :: 4.1
Classifier: Framework :: Django :: 4.2
Classifier: Intended Audience :: Developers
Classifier: License :: OSI Approved :: MIT License
Classifier: Natural Language :: Spanish
Classifier: Operating System :: OS Independent
Classifier: Programming Language :: Python
Classifier: Programming Language :: Python :: 3
Classifier: Programming Language :: Python :: 3.8
Classifier: Programming Language :: Python :: 3.9
Classifier: Programming Language :: Python :: 3.10
Classifier: Topic :: Utilities
Classifier: Topic :: System :: Logging
Classifier: Topic :: System :: Monitoring
Classifier: Topic :: Internet :: WWW/HTTP
Classifier: Topic :: Internet :: WWW/HTTP :: Dynamic Content
License-File: LICENSE
Requires-Dist: django>=3.2
Requires-Dist: django-admin-list-filter-dropdown>=1.0
